pinksale/__init__.py
pinksale/constants.py
pinksale/decorators.py
pinksale/exceptions.py
pinksale/pinksale.py
pinksale/typez.py
pinksale/utils.py
pinksale/assets/pinksale.json
pinksale_python-0.1.6.dist-info/METADATA
pinksale_python-0.1.6.dist-info/WHEEL
pinksale_python-0.1.6.dist-info/top_level.txt
pinksale_python-0.1.6.dist-info/RECORD
