Metadata-Version: 2.1
Name: pinksale-python
Version: 0.1.6
Summary: The unofficial Python client for the Pinksale.
Home-page: https://github.com/hkey0/pinksale-python
Author: hkey
License: UNKNOWN
Platform: UNKNOWN
Requires-Dist: web3
